{
  "type": "minecraft:fishing",
  "pools": [
    {
      "name": "fishing_end",
      "rolls": 1,
      "entries": [
        {
          "type": "minecraft:loot_table",
          "name": "advanced_fishing:gameplay/fishing/end/tier_1",
          "weight": 52,
          "quality": 4
        },
        {
          "type": "minecraft:loot_table",
          "name": "advanced_fishing:gameplay/fishing/end/tier_2",
          "weight": 32,
          "quality": 7
        },
        {
          "type": "minecraft:loot_table",
          "name": "advanced_fishing:gameplay/fishing/end/tier_3",
          "weight": 16,
          "quality": 6
        }
      ]
    }
  ]
}